{
  "properties": [
    {
      "name": "urlfetcher.domains",
      "type": "java.util.Map<java.lang.String, org.open4goods.services.urlfetching.config.UrlFetcherConfig$DomainConfig>",
      "description": "Map of domain configurations for URL fetching. Supported strategies are HTTP, PROXIFIED, and PLAYWRIGHT."
    },
    {
      "name": "urlfetcher.threadPoolSize",
      "type": "int",
      "defaultValue": 10,
      "description": "Thread pool size for asynchronous URL fetching"
    },
    {
      "name": "urlfetcher.record.enabled",
      "type": "boolean",
      "defaultValue": false,
      "description": "Flag to enable or disable recording mode (for test purposes only)"
    },
    {
      "name": "urlfetcher.record.destinationFolder",
      "type": "java.lang.String",
      "defaultValue": "src/test/resources/urlfetching/mocks",
      "description": "Destination folder for storing/retrieving recorded responses (used only in tests)"
    },
    {
      "name": "urlfetcher.domains.*.playwrightProxyFallbackEnabled",
      "type": "boolean",
      "defaultValue": false,
      "description": "When true, failed or empty Playwright fetches are replayed with the domain proxy configuration."
    },
    {
      "name": "urlfetcher.domains.*.playwrightProxyRequired",
      "type": "boolean",
      "defaultValue": false,
      "description": "When true, Playwright starts every fetch for the domain through the configured proxy."
    },
    {
      "name": "urlfetcher.domains.*.proxy.scheme",
      "type": "java.lang.String",
      "defaultValue": "http",
      "description": "Proxy scheme used by proxified HTTP and Playwright proxy fallback."
    },
    {
      "name": "urlfetcher.domains.*.proxy.host",
      "type": "java.lang.String",
      "description": "Proxy host used by proxified HTTP and Playwright proxy fallback."
    },
    {
      "name": "urlfetcher.domains.*.proxy.port",
      "type": "int",
      "description": "Proxy port used by proxified HTTP and Playwright proxy fallback."
    },
    {
      "name": "urlfetcher.domains.*.proxy.username",
      "type": "java.lang.String",
      "description": "Optional proxy username used by Playwright proxy fallback."
    },
    {
      "name": "urlfetcher.domains.*.proxy.password",
      "type": "java.lang.String",
      "description": "Optional proxy password used by Playwright proxy fallback."
    }
  ]
}
